README.txt
setup.py
lib/root2matplot/__init__.py
lib/root2matplot/core.py
lib/root2matplot/overlayHists.py
lib/root2matplot/tree2hists.py
lib/root2matplot.egg-info/PKG-INFO
lib/root2matplot.egg-info/SOURCES.txt
lib/root2matplot.egg-info/dependency_links.txt
lib/root2matplot.egg-info/entry_points.txt
lib/root2matplot.egg-info/top_level.txt