Metadata-Version: 1.0
Name: root2matplot
Version: 0.9.3.1
Summary: Tools for use with ROOT; deprecated in favor of rootplot
Home-page: http://packages.python.org/root2matplot/
Author: Jeff Klukas
Author-email: klukas@wisc.edu
License: UNKNOWN
Platform: UNKNOWN
Classifier: Development Status :: 3 - Alpha
Classifier: Intended Audience :: Science/Research
Classifier: License :: Free for non-commercial use
Classifier: Natural Language :: English
Classifier: Topic :: Scientific/Engineering :: Visualization
Classifier: Topic :: Utilities
